pdi/__init__.py
pdi/categoricals.py
pdi/drop.py
pdi/levels.py
pdi/testing.py
pdi/visuals.py
pandas_illustrated-0.6.dist-info/METADATA
pandas_illustrated-0.6.dist-info/WHEEL
pandas_illustrated-0.6.dist-info/top_level.txt
pandas_illustrated-0.6.dist-info/RECORD
