Metadata-Version: 2.1
Name: pandas-illustrated
Version: 0.6
Summary: Helper functions from the Pandas Illustrated guide
Home-page: https://github.com/axil/pandas-illustrated
Author: Lev Maximov
Author-email: lev.maximov@gmail.com
License: MIT License
Keywords: find,findall,insert,drop,levels,sidebyside,pandas
Platform: UNKNOWN
Classifier: Development Status :: 4 - Beta
Classifier: License :: OSI Approved :: MIT License
Classifier: Operating System :: OS Independent
Classifier: Programming Language :: Python :: 3.7
Classifier: Programming Language :: Python :: 3.8
Classifier: Programming Language :: Python :: 3.9
Classifier: Programming Language :: Python :: 3.10
Classifier: Programming Language :: Python :: 3.11
Requires-Python: >=3.7
Requires-Dist: pandas
Requires-Dist: bs4
Requires-Dist: lxml
Requires-Dist: IPython
